startpageapi/__init__.py
startpageapi/async_client.py
startpageapi/client.py
startpageapi/endpoints.py
startpageapi/exceptions.py
startpageapi/parser.py
startpageapi-0.1.0.dist-info/licenses/LICENSE
startpageapi-0.1.0.dist-info/METADATA
startpageapi-0.1.0.dist-info/WHEEL
startpageapi-0.1.0.dist-info/top_level.txt
startpageapi-0.1.0.dist-info/RECORD
