Metadata-Version: 2.4
Name: startpageapi
Version: 0.1.0
Summary: The StartpageAPI is an unofficial Python library that facilitates access to search results from the Startpage.com engine.
Home-page: https://github.com/deepnor/startpageapi
Author: deepnor
Author-email: deepnor <nothellnor@gmail.com>
License: MIT
Project-URL: Homepage, https://github.com/deepnor/startpageapi
Project-URL: Bug Tracker, https://github.com/deepnor/startpageapi/issues
Project-URL: Documentation, https://github.com/deepnor/startpageapi
Project-URL: Source Code, https://github.com/deepnor/startpageapi
Keywords: search,startpage,api,web scraping,search engine
Classifier: Programming Language :: Python :: 3
Classifier: Programming Language :: Python :: 3.7
Classifier: Programming Language :: Python :: 3.8
Classifier: Programming Language :: Python :: 3.9
Classifier: Programming Language :: Python :: 3.10
Classifier: Programming Language :: Python :: 3.11
Classifier: License :: OSI Approved :: MIT License
Classifier: Operating System :: OS Independent
Classifier: Topic :: Internet :: WWW/HTTP :: Indexing/Search
Classifier: Topic :: Software Development :: Libraries :: Python Modules
Classifier: Intended Audience :: Developers
Classifier: Development Status :: 4 - Beta
Requires-Python: >=3.7
License-File: LICENSE
Requires-Dist: beautifulsoup4>=4.9.0
Requires-Dist: lxml>=4.6.0
Dynamic: author
Dynamic: home-page
Dynamic: license-file
Dynamic: requires-python
